bounden/VERSION
bounden/__init__.py
bounden/log.py
bounden/protocols.py
bounden/py.typed
bounden/region.py
bounden/region2.py
bounden/resolve.py
bounden/types.py
bounden/vectors.py
bounden/volume.py
bounden/volume2.py
bounden/axes/__init__.py
bounden/axes/axis.py
bounden/axes/axis_operation.py
bounden/axes/float_axis.py
bounden/axes/integer_axis.py
bounden/axes/library.py
bounden/axes/no_axis_for_type.py
bounden/axes/py.typed
bounden/axes/string_axis.py
bounden/axes/types.py
bounden/enums/__init__.py
bounden/enums/alignment.py
bounden/enums/py.typed
bounden/points/__init__.py
bounden/points/point.py
bounden/points/point2.py
bounden/points/py.typed
bounden/resolution/__init__.py
bounden/resolution/py.typed
bounden/resolution/region_resolver.py
bounden/resolution/types.py
bounden/resolved/__init__.py
bounden/resolved/py.typed
bounden/resolved/resolved_point.py
bounden/resolved/resolved_volume.py
bounden-1.0.0b21.dist-info/LICENSE
bounden-1.0.0b21.dist-info/METADATA
bounden-1.0.0b21.dist-info/WHEEL
bounden-1.0.0b21.dist-info/top_level.txt
bounden-1.0.0b21.dist-info/RECORD
