Metadata-Version: 2.1
Name: bounden
Version: 1.0.0b21
Summary: Bounds and positions
Home-page: https://bounden.dev
Author: Cariad Eccleston
Author-email: cariad@cariad.earth
License: MIT
Project-URL: Documentation, https://bounden.dev
Project-URL: Funding, https://github.com/sponsors/cariad
Project-URL: Issues, https://github.com/cariad/bounden/issues
Project-URL: Source, https://github.com/cariad/bounden
Classifier: Development Status :: 4 - Beta
Classifier: License :: OSI Approved :: MIT License
Classifier: Natural Language :: English
Classifier: Operating System :: OS Independent
Classifier: Programming Language :: Python :: 3 :: Only
Classifier: Programming Language :: Python :: 3.10
Classifier: Programming Language :: Python :: 3.11
Classifier: Typing :: Typed
Requires-Python: >=3.10
License-File: LICENSE
Requires-Dist: rebelbase (==1.0.0a7)
Requires-Dist: vinculum (==1.0.0b6)
